respan_sdk/__init__.py
respan_sdk/constants/__init__.py
respan_sdk/constants/_internal_constants.py
respan_sdk/constants/dataset_constants.py
respan_sdk/constants/evaluation_constants.py
respan_sdk/constants/experiment_constants.py
respan_sdk/constants/llm_logging.py
respan_sdk/constants/prompt_constants.py
respan_sdk/respan_types/__init__.py
respan_sdk/respan_types/_internal_types.py
respan_sdk/respan_types/base_types.py
respan_sdk/respan_types/chat_completion_types.py
respan_sdk/respan_types/dataset_types.py
respan_sdk/respan_types/eval_types.py
respan_sdk/respan_types/evaluator_types.py
respan_sdk/respan_types/experiment_types.py
respan_sdk/respan_types/filter_types.py
respan_sdk/respan_types/generic_types.py
respan_sdk/respan_types/log_types.py
respan_sdk/respan_types/mixin_types/__init__.py
respan_sdk/respan_types/mixin_types/filter_mixin.py
respan_sdk/respan_types/monitoring_types.py
respan_sdk/respan_types/param_types.py
respan_sdk/respan_types/prompt_types.py
respan_sdk/respan_types/services_types/__init__.py
respan_sdk/respan_types/services_types/assembly_ai_types.py
respan_sdk/respan_types/services_types/linkup_types.py
respan_sdk/respan_types/services_types/mem0_types.py
respan_sdk/respan_types/services_types/moda_types.py
respan_sdk/respan_types/span_types.py
respan_sdk/respan_types/user_types.py
respan_sdk/utils/__init__.py
respan_sdk/utils/bgcolors.py
respan_sdk/utils/crypto.py
respan_sdk/utils/data_processing/__init__.py
respan_sdk/utils/data_processing/id_processing.py
respan_sdk/utils/debug_print.py
respan_sdk/utils/mixins.py
respan_sdk/utils/pre_processing.py
respan_sdk/utils/serialization.py
respan_sdk/utils/time.py
respan_sdk-1.0.0.dist-info/METADATA
respan_sdk-1.0.0.dist-info/WHEEL
respan_sdk-1.0.0.dist-info/RECORD
