Metadata-Version: 2.1
Name: respan-sdk
Version: 1.0.0
Summary: Respan SDK allows you to interact with the Respan API smoothly
License: MIT
Author: Respan
Author-email: team@respan.ai
Requires-Python: >3.9,<4.0
Classifier: License :: OSI Approved :: MIT License
Classifier: Programming Language :: Python :: 3
Classifier: Programming Language :: Python :: 3.10
Classifier: Programming Language :: Python :: 3.11
Classifier: Programming Language :: Python :: 3.12
Provides-Extra: dev
Requires-Dist: dateparser (>=1.2.0,<2.0.0)
Requires-Dist: pydantic (>=2.10.3,<3.0.0)
Requires-Dist: requests (>=2.31.0,<3.0.0)
Requires-Dist: typing-extensions (>=4.12.2,<5.0.0)
